paddlespeech/__init__.py
paddlespeech/audio/__init__.py
paddlespeech/audio/backends/__init__.py
paddlespeech/audio/backends/common.py
paddlespeech/audio/backends/soundfile_backend.py
paddlespeech/audio/compliance/__init__.py
paddlespeech/audio/compliance/kaldi.py
paddlespeech/audio/compliance/librosa.py
paddlespeech/audio/datasets/__init__.py
paddlespeech/audio/datasets/dataset.py
paddlespeech/audio/datasets/esc50.py
paddlespeech/audio/datasets/voxceleb.py
paddlespeech/audio/functional/__init__.py
paddlespeech/audio/functional/functional.py
paddlespeech/audio/functional/window.py
paddlespeech/audio/streamdata/__init__.py
paddlespeech/audio/streamdata/autodecode.py
paddlespeech/audio/streamdata/cache.py
paddlespeech/audio/streamdata/compat.py
paddlespeech/audio/streamdata/extradatasets.py
paddlespeech/audio/streamdata/filters.py
paddlespeech/audio/streamdata/gopen.py
paddlespeech/audio/streamdata/handlers.py
paddlespeech/audio/streamdata/mix.py
paddlespeech/audio/streamdata/paddle_utils.py
paddlespeech/audio/streamdata/pipeline.py
paddlespeech/audio/streamdata/shardlists.py
paddlespeech/audio/streamdata/soundfile.py
paddlespeech/audio/streamdata/tariterators.py
paddlespeech/audio/streamdata/utils.py
paddlespeech/audio/streamdata/writer.py
paddlespeech/audio/text/__init__.py
paddlespeech/audio/text/text_featurizer.py
paddlespeech/audio/text/utility.py
paddlespeech/audio/transform/__init__.py
paddlespeech/audio/transform/add_deltas.py
paddlespeech/audio/transform/channel_selector.py
paddlespeech/audio/transform/cmvn.py
paddlespeech/audio/transform/functional.py
paddlespeech/audio/transform/perturb.py
paddlespeech/audio/transform/spec_augment.py
paddlespeech/audio/transform/spectrogram.py
paddlespeech/audio/transform/transform_interface.py
paddlespeech/audio/transform/transformation.py
paddlespeech/audio/transform/wpe.py
paddlespeech/audio/utils/__init__.py
paddlespeech/audio/utils/check_kwargs.py
paddlespeech/audio/utils/download.py
paddlespeech-1.5.0.dist-info/LICENSE
paddlespeech-1.5.0.dist-info/METADATA
paddlespeech-1.5.0.dist-info/WHEEL
paddlespeech-1.5.0.dist-info/entry_points.txt
paddlespeech-1.5.0.dist-info/top_level.txt
paddlespeech-1.5.0.dist-info/zip-safe
paddlespeech-1.5.0.dist-info/RECORD
