Metadata-Version: 2.1
Name: paddlespeech
Version: 1.5.0
Summary: Speech tools and models based on Paddlepaddle
Home-page: https://github.com/PaddlePaddle/PaddleSpeech
Author: PaddlePaddle Speech and Language Team
Author-email: paddlesl@baidu.com
License: Apache 2.0
Keywords: SSLspeech,asr,tts,speaker verfication,speech classfication,text frontend,MFA,paddlepaddle,paddleaudio,streaming asr,streaming tts,beam search,ctcdecoder,deepspeech2,wav2vec2,hubert,wavlm,transformer,conformer,fastspeech2,hifigan,gan vocoders
Classifier: Development Status :: 5 - Production/Stable
Classifier: Intended Audience :: Developers
Classifier: Intended Audience :: Science/Research
Classifier: Topic :: Scientific/Engineering :: Artificial Intelligence
Classifier: License :: OSI Approved :: Apache Software License
Classifier: Programming Language :: Python
Classifier: Programming Language :: Python :: 3
Classifier: Programming Language :: Python :: 3.8
Classifier: Programming Language :: Python :: 3.9
Classifier: Programming Language :: Python :: 3.10
Requires-Python: >=3.7
License-File: LICENSE
Requires-Dist: braceexpand
Requires-Dist: editdistance
Requires-Dist: g2p-en
Requires-Dist: g2pM
Requires-Dist: h5py
Requires-Dist: hyperpyyaml
Requires-Dist: inflect
Requires-Dist: jsonlines
Requires-Dist: numpy
Requires-Dist: librosa >=0.9
Requires-Dist: scipy
Requires-Dist: loguru
Requires-Dist: matplotlib
Requires-Dist: nara-wpe
Requires-Dist: onnxruntime >=1.11.0
Requires-Dist: opencc
Requires-Dist: opencc-python-reimplemented
Requires-Dist: pandas
Requires-Dist: paddlenlp >=2.4.8
Requires-Dist: paddleslim >=2.3.4
Requires-Dist: ppdiffusers >=0.9.0
Requires-Dist: paddlespeech-feat
Requires-Dist: praatio >=6.0.0
Requires-Dist: prettytable
Requires-Dist: pydantic
Requires-Dist: pypinyin
Requires-Dist: pypinyin-dict
Requires-Dist: python-dateutil
Requires-Dist: pyworld >=0.2.12
Requires-Dist: pyyaml
Requires-Dist: resampy
Requires-Dist: sacrebleu
Requires-Dist: soundfile
Requires-Dist: textgrid
Requires-Dist: timer
Requires-Dist: ToJyutping
Requires-Dist: typeguard
Requires-Dist: webrtcvad
Requires-Dist: yacs >=0.1.8
Requires-Dist: zhon
Requires-Dist: scikit-learn
Requires-Dist: pathos
Requires-Dist: kaldiio
Requires-Dist: ffmpeg-python
Requires-Dist: ffmpy
Requires-Dist: flatten-dict
Requires-Dist: pyloudnorm
Requires-Dist: rich
Requires-Dist: pattern-singleton
Requires-Dist: websockets
Provides-Extra: develop
Requires-Dist: ConfigArgParse ; extra == 'develop'
Requires-Dist: coverage ; extra == 'develop'
Requires-Dist: gpustat ; extra == 'develop'
Requires-Dist: paddlespeech-ctcdecoders ; extra == 'develop'
Requires-Dist: phkit ; extra == 'develop'
Requires-Dist: pypi-kenlm ; extra == 'develop'
Requires-Dist: snakeviz ; extra == 'develop'
Requires-Dist: sox ; extra == 'develop'
Requires-Dist: soxbindings ; extra == 'develop'
Requires-Dist: unidecode ; extra == 'develop'
Requires-Dist: yq ; extra == 'develop'
Requires-Dist: pre-commit ; extra == 'develop'
Provides-Extra: doc
Requires-Dist: sphinx ; extra == 'doc'
Requires-Dist: sphinx-rtd-theme ; extra == 'doc'
Requires-Dist: numpydoc ; extra == 'doc'
Requires-Dist: myst-parser ; extra == 'doc'
Requires-Dist: recommonmark >=0.5.0 ; extra == 'doc'
Requires-Dist: sphinx-markdown-tables ; extra == 'doc'
Requires-Dist: sphinx-autobuild ; extra == 'doc'
Provides-Extra: test
Requires-Dist: nose ; extra == 'test'
Requires-Dist: torchaudio ==0.10.2 ; extra == 'test'
